{"default_values": {"MSSubClass": 50.0, "MSZoning": 3.0, "LotFrontage": 4.248495242049359, "LotArea": 9.156886838722746, "Street": 1.0, "Alley": 1.0, "LotShape": 3.0, "LandContour": 3.0, "Utilities": 0.0, "LotConfig": 4.0, "LandSlope": 0.0, "Neighborhood": 12.0, "Condition1": 2.0, "Condition2": 2.0, "BldgType": 0.0, "HouseStyle": 2.0, "OverallQual": 6.0, "OverallCond": 5.0, "YearBuilt": 1973.0, "YearRemodAdd": 1994.0, "RoofStyle": 1.0, "RoofMatl": 1.0, "Exterior1st": 12.0, "Exterior2nd": 13.0, "MasVnrType": 2.0, "MasVnrArea": 0.0, "ExterQual": 3.0, "ExterCond": 4.0, "Foundation": 1.0, "BsmtQual": 2.0, "BsmtCond": 4.0, "BsmtExposure": 3.0, "BsmtFinType1": 2.0, "BsmtFinSF1": 5.951942943437755, "BsmtFinType2": 6.0, "BsmtFinSF2": 0.0, "BsmtUnfSF": 6.170651297395139, "TotalBsmtSF": 6.900226885665022, "Heating": 1.0, "HeatingQC": 0.0, "CentralAir": 1.0, "Electrical": 4.0, "1stFlrSF": 6.992096005027085, "2ndFlrSF": 0.0, "LowQualFinSF": 0.0, "GrLivArea": 7.289610521451167, "BsmtFullBath": 0.0, "BsmtHalfBath": 0.0, "FullBath": 2.0, "HalfBath": 0.0, "BedroomAbvGr": 3.0, "KitchenAbvGr": 1.0, "KitchenQual": 3.0, "TotRmsAbvGrd": 6.0, "Functional": 6.0, "Fireplaces": 1.0, "FireplaceQu": 3.0, "GarageType": 1.0, "GarageYrBlt": 1980.0, "GarageFinish": 2.0, "GarageCars": 2.0, "GarageArea": 480.0, "GarageQual": 5.0, "GarageCond": 5.0, "PavedDrive": 2.0, "WoodDeckSF": 0.0, "OpenPorchSF": 3.258096538021482, "EnclosedPorch": 0.0, "3SsnPorch": 0.0, "ScreenPorch": 0.0, "PoolArea": 0.0, "PoolQC": 3.0, "Fence": 4.0, "MiscFeature": 1.0, "MiscVal": 0.0, "MoSold": 6.0, "YrSold": 2008.0, "SaleType": 8.0, "SaleCondition": 4.0, "TotalSF": 7.8139955933784595, "TotalBath": 2.0, "TotalPorchSF": 3.8918202981106265, "HouseAge": 35.0, "RemodelAge": 14.0, "HasRemodel": 0.0, "HasGarage": 1.0, "HasBsmt": 1.0, "HasFireplace": 1.0, "Has2ndFloor": 0.0, "HasWoodDeck": 0.0, "HasOpenPorch": 1.0, "HasPool": 0.0, "LotPerSF": 1.560619953103549, "GarageRatio": 0.18265269674250134, "OverallQual2": 36.0, "OverallQual3": 216.0, "QualPerSF": 0.002438978445674347, "YearBuilt2": 3892729.0, "TotalRooms": 8.0, "AvgRoomSize": 5.284245524818591}, "skew_cols": ["LotFrontage", "LotArea", "MasVnrArea", "BsmtFinSF1", "BsmtFinSF2", "BsmtUnfSF", "TotalBsmtSF", "1stFlrSF", "2ndFlrSF", "LowQualFinSF", "GrLivArea", "WoodDeckSF", "OpenPorchSF", "EnclosedPorch", "3SsnPorch", "ScreenPorch", "PoolArea", "MiscVal", "TotalSF", "TotalPorchSF", "LotPerSF", "QualPerSF", "AvgRoomSize"]}